cara_api/__init__ 2.py
cara_api/__init__.py
cara_api-1.6.2.dist-info/LICENSE
cara_api-1.6.2.dist-info/METADATA
cara_api-1.6.2.dist-info/WHEEL
cara_api-1.6.2.dist-info/top_level.txt
cara_api-1.6.2.dist-info/RECORD
