Metadata-Version: 2.1
Name: cara_api
Version: 1.6.2
Summary: Allows you to interact with the Cara API.
Author: Red_Wolf2467
Author-email: support@pyropixle.com
Requires-Python: >=3.8
License-File: LICENSE
Requires-Dist: requests
Requires-Dist: reds-simple-logger
